{
  "types": ["feat", "fix", "docs", "chore", "refactor", "test", "style"],
  "askScope": true,
  "scopes": ["auth", "ui", "api", "db", "config"],
  "askTicket": false,
  "askBreaking": true,
  "format": "{type}({scope}): {message}",
  "headerMaxLength": 72,
  "ai": {
    "enabled": true,
    "provider": "nvidia",
    "model": "nvidia/llama-3.3-nemotron-super-49b-v1",
    "endpoint": "https://integrate.api.nvidia.com/v1/chat/completions",
    "askByDefault": true,
    "allowNewScopes": true
  }
}
